README.rst
setup.cfg
setup.py
django_oscar_mpesa.egg-info/PKG-INFO
django_oscar_mpesa.egg-info/SOURCES.txt
django_oscar_mpesa.egg-info/dependency_links.txt
django_oscar_mpesa.egg-info/pbr.json
django_oscar_mpesa.egg-info/requires.txt
django_oscar_mpesa.egg-info/top_level.txt
mpesa/__init__.py
mpesa/admin.py
mpesa/app.py
mpesa/config.py
mpesa/forms.py
mpesa/handlers.py
mpesa/models.py
mpesa/processing.py
mpesa/utils.py
mpesa/dashboard/__init__.py
mpesa/dashboard/app.py
mpesa/dashboard/config.py
mpesa/dashboard/views.py
mpesa/migrations/0001_initial.py
mpesa/migrations/0001_squashed_0005_auto_20150824_1603.py
mpesa/migrations/0002_auto_20141013_1222.py
mpesa/migrations/0002_auto_20150825_1513.py
mpesa/migrations/0003_auto_20141015_1142.py
mpesa/migrations/0003_auto_20150825_1513.py
mpesa/migrations/0004_auto_20141021_1539.py
mpesa/migrations/0004_auto_20150825_1543.py
mpesa/migrations/0005_auto_20150824_1603.py
mpesa/migrations/0005_auto_20150825_1753.py
mpesa/migrations/__init__.py
mpesa/signals/__init__.py
mpesa/signals/handlers.py
mpesa/views/__init__.py
mpesa/views/checkout_views.py
mpesa/views/ipn_views.py